{
    "id": "com.giadamusic.Giada",
    "runtime": "org.freedesktop.Platform",
    "sdk": "org.freedesktop.Sdk//19.08",
    "runtime-version": "19.08",
    "command": "giada",
    "finish-args": [
        /* X11 + XShm access */
        "--share=ipc",
        "--socket=x11",
        /* Note playback */
        "--socket=pulseaudio",
        /* MIDI */
        "--device=all",
        /* Allow loading, saving files from anywhere (portals don’t work yet) */
        "--filesystem=home",
        /* Allow other instances to see lockfiles */
        "--env=TMPDIR=/var/tmp",
        "--env=VST_PATH=/app/extensions/VstPlugins/lxvst"
    ],
    "add-extensions": {
        "org.freedesktop.LinuxAudio.Plugins": {
            "directory": "extensions/Plugins",
            "version": "19.08",
            "add-ld-path": "lib",
            "merge-dirs": "lxvst",
            "subdirectories": true,
            "no-autodownload": true
        },
        "org.freedesktop.LinuxAudio.VstPlugins": {
            "directory": "extensions/VstPlugins",
            "version": "19.08",
            "add-ld-path": "lib",
            "merge-dirs": "lxvst",
            "subdirectories": true,
            "no-autodownload": true
        }
    },
    "cleanup": [
        "/bin/jack*",
        "/bin/alsa*"
    ],
    "modules": [
        {
            "name": "fltk",
            "config-opts": [
                "--enable-threads",
                "--enable-cairo",
                "--enable-shared",
                "--disable-static"
            ],
            "sources": [
                {
                    "type": "archive",
                    "url": "https://github.com/fltk/fltk/archive/release-1.3.5.tar.gz",
                    "sha256": "5c534287b0e03b9520ff866704a5649268986b371bdf8f6ac003fa240e761901"
                }
            ],
            "cleanup": [
                "/bin",
                "/include",
                "/man",
                "/share/doc",
                "/share/man",
                "/lib/pkgconfig",
                "*.so",
                "*.la",
                "*.a"
            ]
        },
        {
            "name": "rtmidi",
            "cleanup": [
                "/include",
                "/lib/pkgconfig",
                "*.la",
                "*.a",
                "*.so"
            ],
            "sources": [
                {
                    "type": "archive",
                    "url": "http://www.music.mcgill.ca/~gary/rtmidi/release/rtmidi-4.0.0.tar.gz",
                    "sha256": "370cfe710f43fbeba8d2b8c8bc310f314338c519c2cf2865e2d2737b251526cd"
                }
            ]
        },
        "shared-modules/linux-audio/jack2.json",
        {
            "name": "giada",
            "buildsystem": "autotools",
            "config_opts": [
                "--target=linux",
                "--enable-vst"
            ],
            "cleanup": [],
            "post_install": [
                "install -Dm0644 extras/giada-logo.png /app/share/icons/com.giadamusic.Giada.png",
                "install -Dm0644 -t /app/share/metainfo com.giadamusic.Giada.appdata.xml",
                "install -Dm0644 -t /app/share/applications com.giadamusic.Giada.desktop",
                "install -d /app/extensions/Plugins",
                "install -d /app/extensions/VstPlugins"
            ],
            "sources": [
                {
                    "type": "archive",
                    "url": "https://www.giadamusic.com/data/giada-0.16.3.1-src.tar.gz",
                    "sha256": "70979ec9346d5e16dd2628e6ccb0bdbabe9fcff9b7c5333c15347c139f23a189"
                },
                {
                    "type": "patch",
                    "path": "giada-juce.patch"
                },
                {
                    "type": "file",
                    "path": "com.giadamusic.Giada.desktop"
                },
                {
                    "type": "file",
                    "path": "com.giadamusic.Giada.appdata.xml"
                }
            ]
        }
    ]
}
