{
	"app-id": "com.adilhanney.no_more_background",
	"runtime": "org.freedesktop.Platform",
	"runtime-version": "25.08",
	"sdk": "org.freedesktop.Sdk",
	"command": "no_more_background",
	"separate-locales": false,
	"finish-args": [
		"--share=ipc",
		"--share=network",
		"--socket=fallback-x11",
		"--socket=wayland",
		"--device=all",
		"--filesystem=~/Android/Sdk/platform-tools/adb:ro",
		"--filesystem=/usr/bin/adb:ro",
		"--env=PATH=~/Android/Sdk/platform-tools:/app/bin:/usr/bin"
	],
	"modules": [
		{
			"name": "adb",
			"only-arches": [
				"x86_64"
			],
			"buildsystem": "simple",
			"build-commands": [
				"install -D adb /app/bin/adb"
			],
			"sources": [
				{
					"type": "archive",
					"url": "https://dl.google.com/android/repository/platform-tools_r36.0.0-linux.zip",
					"sha256": "0ead642c943ffe79701fccca8f5f1c69c4ce4f43df2eefee553f6ccb27cbfbe8"
				}
			]
		},
		{
			"name": "no_more_background",
			"buildsystem": "simple",
			"build-commands": [
				"mkdir -p /app",
				"tar -xf NoMoreBackground_*.tar.gz -C /app",
				"mkdir -p /app/bin",
				"ln -s /app/no_more_background /app/bin/no_more_background"
			],
			"sources": [
				{
					"type": "file",
					"url": "https://github.com/adil192/no_more_background/releases/download/v0.1.1/NoMoreBackground_Linux_x86_64.tar.gz",
					"sha256": "3e17e05abb9aa1c74818960928a91526d0776493809bf800d3362627823840ef",
					"only-arches": [
						"x86_64"
					],
					"x-checker-data": {
						"type": "json",
						"url": "https://api.github.com/repos/adil192/no_more_background/releases/latest",
						"version-query": ".tag_name",
						"url-query": ".assets[] | select(.name==\"NoMoreBackground_Linux_x86_64.tar.gz\") | .browser_download_url"
					}
				},
				{
					"type": "file",
					"url": "https://github.com/adil192/no_more_background/releases/download/v0.1.1/NoMoreBackground_Linux_arm64.tar.gz",
					"sha256": "79cae4a013847aec974ad8577dd7f8a899e9508f23f51bf353d406010da2dd06",
					"only-arches": [
						"aarch64"
					],
					"x-checker-data": {
						"type": "json",
						"url": "https://api.github.com/repos/adil192/no_more_background/releases/latest",
						"version-query": ".tag_name",
						"url-query": ".assets[] | select(.name==\"NoMoreBackground_Linux_arm64.tar.gz\") | .browser_download_url"
					}
				}
			]
		}
	]
}
