{
    "app-id" : "com.lakoliu.Furtherance",
    "runtime" : "org.gnome.Platform",
    "runtime-version" : "42",
    "sdk" : "org.gnome.Sdk",
    "sdk-extensions" : [
        "org.freedesktop.Sdk.Extension.rust-stable"
    ],
    "command" : "furtherance",
    "finish-args" : [
        "--share=ipc",
        "--socket=fallback-x11",
        "--device=dri",
        "--socket=wayland",
        "--talk-name=org.gnome.Mutter.IdleMonitor"
    ],
    "build-options" : {
        "append-path" : "/usr/lib/sdk/rust-stable/bin",
        "env" : {
            "RUST_BACKTRACE" : "1",
            "RUST_LOG" : "furtherance=debug"
        }
    },
    "cleanup" : [
        "/include",
        "/lib/pkgconfig",
        "/man",
        "/share/doc",
        "/share/gtk-doc",
        "/share/man",
        "/share/pkgconfig",
        "*.la",
        "*.a"
    ],
    "modules" : [
        {
            "name":"libsass",
            "sources":[
                {
                    "type":"archive",
                    "url":"https://github.com/sass/libsass/archive/3.6.4.tar.gz",
                    "sha256":"f9484d9a6df60576e791566eab2f757a97fd414fce01dd41fc0a693ea5db2889"
                },
                {
                    "type":"script",
                    "dest-filename":"autogen.sh",
                    "commands":[
                        "autoreconf -si"
                    ]
                }
            ]
        },
        {
            "name":"sassc",
            "sources":[
                {
                    "type":"archive",
                    "url":"https://github.com/sass/sassc/archive/3.6.1.tar.gz",
                    "sha256":"8cee391c49a102b4464f86fc40c4ceac3a2ada52a89c4c933d8348e3e4542a60"
                },
                {
                    "type":"script",
                    "dest-filename":"autogen.sh",
                    "commands":[
                        "autoreconf -si"
                    ]
                }
            ]
        },
        {
            "name":"gtk",
            "buildsystem":"meson",
            "config-opts":[
                "-Dbuild-examples=false",
                "-Dbuild-tests=false",
                "-Dintrospection=disabled"
            ],
            "sources":[
                {
                    "type":"archive",
                    "url":"https://download.gnome.org/sources/gtk/4.6/gtk-4.6.2.tar.xz",
                    "sha256":"ff263af609a50eb76056653592d929459aef4819a444c436f6d52c6f63c1faec"
                }
            ]
        },
        {
            "name":"libadwaita",
            "buildsystem":"meson",
            "config-opts":[
                "-Dvapi=false",
                "-Dexamples=false",
                "-Dtests=false"
            ],
            "sources":[
                {
                    "type":"archive",
                    "url":"https://download.gnome.org/sources/libadwaita/1.1/libadwaita-1.1.0.tar.xz",
                    "sha256":"aff598803e810cc28266472cf5bf65e5ed5b90bb3523e206b06b14527325010e"
                }
            ]
        },
        {
            "name" : "furtherance",
            "buildsystem" : "meson",
            "sources" : [
                {
                    "type" : "archive",
                    "url" : "https://github.com/lakoliu/Furtherance/releases/download/v1.0.8/furtherance-offline-1.0.8.tar.xz",
                    "sha256" : "9b1f9b23d4e4a75489efe629ba7eda49e2b6805573a182169a547ccfaf6f5004"
                }
            ]
        }
    ]
}
