[
    {
        "type": "git",
        "url": "https://github.com/apple/swift-argument-parser.git",
        "disable-shallow-clone": true,
        "commit": "41982a3656a71c768319979febd796c6fd111d5c",
        "dest": ".build/checkouts/swift-argument-parser"
    },
    {
        "type": "git",
        "url": "https://github.com/apple/swift-cmark.git",
        "disable-shallow-clone": true,
        "commit": "3bc2f3e25df0cecc5dc269f7ccae65d0f386f06a",
        "dest": ".build/checkouts/swift-cmark"
    },
    {
        "type": "git",
        "url": "https://github.com/apple/swift-markdown.git",
        "disable-shallow-clone": true,
        "commit": "4aae40bf6fff5286e0e1672329d17824ce16e081",
        "dest": ".build/checkouts/swift-markdown"
    },
    {
        "type": "git",
        "url": "https://github.com/swiftlang/swift-syntax.git",
        "disable-shallow-clone": true,
        "commit": "51eb17afa905b48907620f91ece81249093e6ac7",
        "dest": ".build/checkouts/swift-syntax"
    },
    {
         "type": "file",
         "path": "setup-offline.sh"
    }
]