{
    "app-id" : "net.hypatiaproject.Hypatia",
    "runtime" : "org.gnome.Platform",
    "runtime-version" : "48",
    "sdk" : "org.gnome.Sdk",
    "command" : "hypatia",
    "finish-args" : [
        "--share=network",
        "--share=ipc",
        "--socket=fallback-x11",
        "--device=dri",
        "--socket=wayland"
    ],
    "cleanup" : [
        "/include",
        "/lib/pkgconfig",
        "/man",
        "/share/doc",
        "/share/gtk-doc",
        "/share/man",
        "/share/pkgconfig",
        "/share/vala",
        "*.la",
        "*.a"
    ],
    "modules" : [
    	"shared-modules/libsoup/libsoup-2.4.json",
        {
            "name" : "hypatia",
            "builddir" : true,
            "buildsystem" : "meson",
            "sources" : [
                {
                    "type" : "archive",
                    "url" : "https://codeberg.org/nathandyer/Hypatia/archive/0.1.4.tar.gz",
                    "sha256" : "a82414df59eed32038e5eb6acd7f9d4dc071014dd0e908c15d61be63ebb5423b"
                }
            ]
        }
    ]
}
