{
    "id": "org.kde.qrca",
    "runtime": "org.kde.Platform",
    "runtime-version": "6.9",
    "sdk": "org.kde.Sdk",
    "command": "qrca",
    "finish-args": [
        "--share=ipc",
        "--share=network",
        "--socket=fallback-x11",
        "--socket=wayland",
        "--device=all",
        "--system-talk-name=org.freedesktop.NetworkManager"
    ],
    "modules": [
        {
            "name": "libndp",
            "buildsystem": "autotools",
            "cleanup": [
                "/bin",
                "/include",
                "/lib/pkgconfig",
                "/share/man"
            ],
            "sources": [
                {
                    "type": "archive",
                    "url": "https://github.com/jpirko/libndp/archive/v1.9.tar.gz",
                    "sha256": "e564f5914a6b1b799c3afa64c258824a801c1b79a29e2fe6525b682249c65261",
                    "x-checker-data": {
                        "type": "anitya",
                        "project-id": 14944,
                        "stable-only": true,
                        "url-template": "https://github.com/jpirko/libndp/archive/v$version.tar.gz"
                    }
                }
            ]
        },
        {
            "name": "polkit",
            "buildsystem": "meson",
            "config-opts": [
                "-Dlibs-only=true",
                "-Dauthfw=shadow"
            ],
            "cleanup": [
                "/bin/*",
                "/include",
                "/etc/pam.d",
                "/etc/dbus-1",
                "/lib/pkgconfig",
                "/lib/polkit-1",
                "/share/dbus-1/system-services/*",
                "/share/polkit-1"
            ],
            "sources": [
                {
                    "type": "archive",
                    "url": "https://github.com/polkit-org/polkit/archive/refs/tags/126.tar.gz",
                    "sha256": "2814a7281989f6baa9e57bd33bbc5e148827e2721ccef22aaf28ab2b376068e8",
                    "x-checker-data": {
                        "type": "anitya",
                        "project-id": 3682,
                        "stable-only": true,
                        "url-template": "https://github.com/polkit-org/polkit/archive/refs/tags/$version.tar.gz"
                    }
                }
            ]
        },
        {
            "name": "NetworkManager",
            "buildsystem": "meson",
            "config-opts": [
                "-Dsystemdsystemunitdir=no",
                "-Ddbus_conf_dir=/app/etc/dbus-1/system.d",
                "-Diptables=/usr/bin/true",
                "-Ddnsmasq=/usr/bin/true",
                "-Dsession_tracking=no",
                "-Dselinux=false",
                "-Dsystemd_journal=false",
                "-Dlibaudit=no",
                "-Dwext=false",
                "-Dwifi=true",
                "-Dppp=false",
                "-Dmodem_manager=false",
                "-Dovs=false",
                "-Dnmcli=false",
                "-Dnmtui=false",
                "-Dintrospection=false",
                "-Dvapi=false",
                "-Ddocs=false",
                "-Dtests=no",
                "-Dfirewalld_zone=false",
                "-Dlibpsl=false",
                "-Dqt=false",
                "-Dnm_cloud_setup=false"
            ],
            "cleanup": [
                "/bin",
                "/etc",
                "/include",
                "/lib/pkgconfig",
                "/libexec",
                "/sbin",
                "/var"
            ],
            "sources": [
                {
                    "type": "archive",
                    "url": "https://gitlab.freedesktop.org/NetworkManager/NetworkManager/-/archive/1.52.0/NetworkManager-1.52.0.tar.gz",
                    "sha256": "2ebe60a1497a9650d58336b73413d838189b04543365b3dbc22e1eb8023d205f",
                    "x-checker-data": {
                        "type": "anitya",
                        "project-id": 21197,
                        "stable-only": true,
                        "url-template": "https://gitlab.freedesktop.org/NetworkManager/NetworkManager/-/archive/$version/NetworkManager-$version.tar.gz"
                    }
                }
            ]
        },
        {
            "name": "networkmanager-qt",
            "buildsystem": "cmake-ninja",
            "config-opts": [
                "-DBUILD_TESTING=OFF",
                "-DCMAKE_BUILD_TYPE=RelWithDebInfo"
            ],
            "sources": [
                {
                    "type": "archive",
                    "url": "https://download.kde.org/stable/frameworks/6.13/networkmanager-qt-6.13.0.tar.xz",
                    "sha256": "9a9e3595a1b9816b2737b0416b9d92b76e2b0ca0989d0ef65a95e5f895ac36c1",
                    "x-checker-data": {
                        "type": "anitya",
                        "project-id": 8762,
                        "stable-only": true,
                        "url-template": "https://download.kde.org/stable/frameworks/$major.$minor/networkmanager-qt-$version.tar.xz"
                    }
                }
            ]
        },
        {
            "name": "kirigami-addons",
            "config-opts": [
                "-DBUILD_TESTING=OFF",
                "-DCMAKE_BUILD_TYPE=RelWithDebInfo"
            ],
            "buildsystem": "cmake-ninja",
            "sources": [
                {
                    "type": "archive",
                    "url": "https://download.kde.org/stable/kirigami-addons/kirigami-addons-1.7.0.tar.xz",
                    "sha256": "7d854975185cf740de486d84f1e2ec3e4eadb66ac9fb897214cba9ab8cc492b1",
                    "x-checker-data": {
                        "type": "anitya",
                        "project-id": 242933,
                        "stable-only": true,
                        "url-template": "https://download.kde.org/stable/kirigami-addons/kirigami-addons-$version.tar.xz"
                    }
                }
            ]
        },
        {
            "name": "qrca",
            "buildsystem": "cmake-ninja",
            "builddir": true,
            "config-opts": [
                "-DCMAKE_BUILD_TYPE=RelWithDebInfo"
            ],
            "sources": [
                {
                    "type": "archive",
                    "url": "https://download.kde.org/stable/release-service/25.04.0/src/qrca-25.04.0.tar.xz",
                    "sha256": "fdd692a2acb9b05a9b80eaece4c353a4c2c8424037fbe9c7b25a878c6f3c56e9",
                    "x-checker-data": {
                        "type": "anitya",
                        "project-id": 261558,
                        "stable-only": true,
                        "url-template": "https://download.kde.org/stable/release-service/$version/src/qrca-$version.tar.xz"
                    }
                }
            ]
        }
    ]
}
