{
    "id": "org.gimp.GIMP.Plugin.Resynthesizer",
    "branch": "2-3.36",
    "runtime": "org.gimp.GIMP",
    "runtime-version": "stable",
    "sdk": "org.gnome.Sdk//3.36",
    "build-extension": true,
    "appstream-compose": false,
    "build-options": {
        "prefix": "/app/extensions/Resynthesizer",
        "prepend-path": "/app/extensions/Resynthesizer/bin"
    },
    "cleanup": [
        "/bin",
        "/share/man"
    ],
    "modules": [
        "shared-modules/intltool/intltool-0.51.json",
        {
            "name": "resynthesizer",
            "build-options": {
                "env": {
                    "ACLOCAL_FLAGS": "-I /app/extensions/Resynthesizer/share/aclocal",
                    "GIMP_LIBDIR": "${FLATPAK_DEST}"
                }
            },
            "post-install": [
                "install -Dm644 gimp-resynthesizer.metainfo.xml ${FLATPAK_DEST}/share/metainfo/org.gimp.GIMP.Plugin.Resynthesizer.metainfo.xml",
                "appstream-compose --basename=org.gimp.GIMP.Plugin.Resynthesizer --prefix=${FLATPAK_DEST} --origin=flatpak org.gimp.GIMP.Plugin.Resynthesizer",
                "mkdir $FLATPAK_DEST/help",
                "mv $FLATPAK_DEST/share/resynthesizer/help $FLATPAK_DEST/help/resynthesizer",
                "install -Dm644 -t $FLATPAK_DEST/share/licenses/resynthesizer COPYING"
            ],
            "sources": [
                {
                    "type": "archive",
                    "url": "https://github.com/bootchk/resynthesizer/archive/v2.0.3.tar.gz",
                    "sha256": "798678095c34b101c880eb350b31e9a6ff9748707d6ad9063cdee26c38016450"
                },
                {
                    "type": "patch",
                    "path": "resynthesizer.patch"
                }
            ]
        }
    ]
}
