{
	"app-id": "se.cendio.tlclient",
	"runtime": "org.freedesktop.Platform",
	"runtime-version": "21.08",
	"sdk": "org.freedesktop.Sdk",
	"command": "tlclient",
	"tags": [
		"proprietary"
	],
	"finish-args": [
		"--filesystem=host",
		"--filesystem=/run/.heim_org.h5l.kcm-socket",
		"--persist=.thinlinc",
		"--share=ipc",
		"--share=network",
		"--socket=cups",
		"--socket=pcsc",
		"--socket=pulseaudio",
		"--socket=x11"
	],
	"modules": [
		"shared-modules/libusb/libusb.json",
		{
			"name": "pcsc-lite",
			"config-opts": [
				"--disable-libudev",
				"--disable-libsystemd",
				"--without-systemdsystemunitdir"
			],
			"sources": [
				{
					"type": "archive",
					"url": "https://pcsclite.apdu.fr/files/pcsc-lite-1.9.5.tar.bz2",
					"sha256": "9ee3f9b333537562177893559ad4f7b8d5c23ebe828eef53056c02db14049d08",
					"x-checker-data": {
						"type": "anitya",
						"project-id": 2611,
						"url-template": "https://pcsclite.apdu.fr/files/pcsc-lite-$version.tar.bz2"
					}
				}
			]
		},
		{
			"name": "cups",
			"buildsystem": "simple",
			"build-commands": [
				"./configure --disable-systemd --enable-threads --enable-gnutls",
				"gcc berkeley/lpr.c -o ${FLATPAK_DEST}/bin/lpr -I . -lcups"
			],
			"sources": [
				{
					"type": "archive",
					"url": "https://github.com/OpenPrinting/cups/releases/download/v2.4.1/cups-2.4.1-source.tar.gz",
					"sha256": "c7339f75f8d4f2dec50c673341a45fc06b6885bb6d4366d6bf59a4e6c10ae178",
					"x-checker-data": {
						"type": "anitya",
						"project-id": 380,
						"stable-only": true,
						"url-template": "https://github.com/OpenPrinting/cups/releases/download/v$version/cups-$version-source.tar.gz"
					}
				}
			]
		},
		{
			"name": "krb5",
			"subdir": "src",
			"config-opts": [
				"--localstatedir=/var/lib",
				"--sbindir=${FLATPAK_DEST}/bin",
				"--disable-static",
				"--disable-rpath"
			],
			"sources": [
				{
					"type": "archive",
					"url": "https://github.com/krb5/krb5/archive/refs/tags/krb5-1.19.3-final.tar.gz",
					"sha256": "131890da54fff2ac339e93facf9d8067f7db53b15181f38104c0b56a6f2acdee",
					"x-checker-data": {
						"type": "anitya",
						"project-id": 13287,
						"stable-only": true,
						"url-template": "https://github.com/krb5/krb5/archive/refs/tags/krb5-$version.tar.gz"
					}
				},
				{
					"type": "shell",
					"dest": "src",
					"commands": [
						"autoreconf -si"
					]
				}
			]
		},
		{
			"name": "thinlinc",
			"buildsystem": "simple",
			"build-commands": [
				"tar -xf thinlinc.tar.gz",
				"mv tl-*-client-linux-dynamic-x86_64/bin/* ${FLATPAK_DEST}/bin",
				"mv tl-*-client-linux-dynamic-x86_64/lib/* ${FLATPAK_DEST}/lib",
				"mv ${FLATPAK_DEST}/lib/tlclient/share/* ${FLATPAK_DEST}/share",
				"mv ${FLATPAK_DEST}/share/applications/thinlinc-client.desktop ${FLATPAK_DEST}/share/applications/${FLATPAK_ID}.desktop",
				"mv ${FLATPAK_DEST}/share/mime/packages/thinlinc-client-mime.xml ${FLATPAK_DEST}/share/mime/packages/${FLATPAK_ID}.xml",
				"desktop-file-edit --set-key=TryExec --set-value=${FLATPAK_DEST}/bin/tlclient-openconf ${FLATPAK_DEST}/share/applications/${FLATPAK_ID}.desktop",
				"desktop-file-edit --set-key=Exec --set-value=\"${FLATPAK_DEST}/bin/tlclient-openconf %f\" ${FLATPAK_DEST}/share/applications/${FLATPAK_ID}.desktop",
				"desktop-file-edit --set-key=Icon --set-value=${FLATPAK_ID} ${FLATPAK_DEST}/share/applications/${FLATPAK_ID}.desktop",
				"rename thinlinc-client ${FLATPAK_ID} ${FLATPAK_DEST}/share/icons/hicolor/*/apps/*",
				"rename application-vnd.cendio.thinlinc.clientconf ${FLATPAK_ID} ${FLATPAK_DEST}/share/icons/hicolor/*/mimetypes/*",
				"install -Dm644 ${FLATPAK_ID}.metainfo.xml -t ${FLATPAK_DEST}/share/metainfo"
			],
			"sources": [
				{
					"type": "file",
					"dest-filename": "thinlinc.tar.gz",
					"only-arches": [
						"x86_64"
					],
					"url": "https://www.cendio.com/downloads/clients/tl-4.14.0-2324-client-linux-dynamic-x86_64.tar.gz",
					"sha256": "81b8e54abe184bda88a04dd827d03e85da528bf93f7f457e838c3c4f97616274",
					"x-checker-data": {
						"type": "html",
						"url": "https://www.cendio.com/thinlinc/download",
						"version-pattern": "<a href=\"/downloads/clients/tl-([\\d\\.-]*)-client-linux-dynamic-x86_64.tar.gz\">64-bit</a>",
						"url-template": "https://www.cendio.com/downloads/clients/tl-${version}-client-linux-dynamic-x86_64.tar.gz"
					}
				},
				{
					"type": "file",
					"path": "se.cendio.tlclient.metainfo.xml"
				}
			]
		}
	]
}
